quickseries/__init__.py
quickseries/approximate.py
quickseries/benchmark.py
quickseries/expansions.py
quickseries/simplefit.py
quickseries/sourceutils.py
quickseries/sputils.py
quickseries-0.2.1.dist-info/LICENSE
quickseries-0.2.1.dist-info/METADATA
quickseries-0.2.1.dist-info/WHEEL
quickseries-0.2.1.dist-info/top_level.txt
quickseries-0.2.1.dist-info/RECORD
